{
    "Фамилия": "Наумов",
    "Имя": "Агата",
    "Отчество": "Ефимьевич",
    "Прежние ФИО": "Попова Фрол Робертовна",
    "Дата рождения": "5/29/1975",
    "Место рождения": "к. Кемерово",
    "СНИЛС": 805577129658,
    "ИНН": 4688674821,
    "Вид документа": "Свидетельство о рождении",
    "Серия и номер": "8,596,484,976",
    "Субъект Российской Федерации": "Ставропольский край",
    "Район": "Центральный",
    "Город": "к. Челюскин",
    "Населенный пункт": "Поселок",
    "Улица": "ш. Спортивное",
    "Номер дома": 148,
    "Номер корпуса": 6,
    "Номер квартиры": 17,
    "Тип недвижимости": "Дача",
    "Вид собственности (недвижимость)": "Государственная",
    "Адрес недвижимости": "наб. Фадеева, д.46, кв.93",
    "Площадь (кв.м)": 170,
    "Основание приобретения (недвижимость)": "Дарение",
    "Стоимость (недвижимость)": 3328914,
    "Залог (недвижимость)": "Нет",
    "Тип транспортного средства": "Иное транспортное средство",
    "Марка (транспорт)": "ИП «Сорокина Кудряшова»",
    "Год изготовления (транспорт)": 1998,
    "Идентификационный номер (VIN)": "FtI-486438",
    "Вид собственности (транспорт)": "Государственная",
    "Место нахождения/хранения (транспорт)": "с. Усть-Кулом, наб. Красногвардейская, д. 3/2, 922766",
    "Стоимость (транспорт)": 2019579,
    "Залог (транспорт)": "Нет",
    "Наименование банка/кредитной организации": "ЗАО «Нестеров, Муравьев и Алексеев» Банк",
    "Адрес банка/кредитной организации": "с. Буденновск, пер. Сенной, д. 5 к. 5/1, 213287",
    "Вид счета": "Сберегательный счет",
    "Валюта счета": "EUR",
    "Дата открытия счета": "4/23/2020",
    "Остаток на счете (руб.)": 3570670,
    "Наименование организации": "Лебедев Лимитед",
    "Организационно-правовая форма": "ООО",
    "Адрес организации": "к. Беломорск, алл. Сиреневая, д. 95, 766132",
    "Уставный капитал (руб.)": 40394436,
    "Паевой фонд (руб.)": 12879559,
    "Доля участия (%)": "95.55",
    "Основание участия": "Вклад в уставный капитал",
    "Вид ценной бумаги": "Акция",
    "Лицо выпустившее ценную бумагу": "ООО «Семенов Цветкова»",
    "Номинальная величина обязательства (руб)": 15273,
    "Общее количество": 2013,
    "Общая стоимость (руб)": 144944,
    "Наличные денежные средства": 436330,
    "Адрес хранения наличных": "пр. Проточный, д.158",
    "Драгоценности": 62611,
    "Адрес хранения драгоценностей": "ул. Профсоюзная, д.30",
    "Предметы искусства": 334604,
    "Адрес хранения предметов искусства": "пр. Советской Армии, д.185",
    "Имущество для профессиональных занятий": 122080,
    "Адрес хранения имущества": "пр. Школьный, д.9",
    "Иное ценное имущество": 167174,
    "Адрес хранения иного имущества": "пр. Стахановский, д.71",
    "Ссылка на документ": "https://docs.google.com/document/d/170YjkxIfTZA4cKvtoZXKQ04nWidzRjHnw6WM83gj8Hs/edit?usp=sharing",
    "ID": "27b04976-0c96-43bc-9a46-3d40ab95020c"
}