{
    "Фамилия": "Смирнова",
    "Имя": "Илья",
    "Отчество": "Ильинична",
    "Прежние ФИО": "Афанасьева Радислав Андреевна",
    "Дата рождения": "1/7/1989",
    "Место рождения": "п. Воскресенск",
    "СНИЛС": 513085933683,
    "ИНН": 7634793655,
    "Вид документа": "Паспорт",
    "Серия и номер": "3,898,888,416",
    "Субъект Российской Федерации": "Чукотский АО",
    "Район": "Южный",
    "Город": "г. Лагань",
    "Населенный пункт": "Поселок",
    "Улица": "пр. Мира",
    "Номер дома": 7,
    "Номер корпуса": 2,
    "Номер квартиры": 6,
    "Тип недвижимости": "Земельный участок",
    "Вид собственности (недвижимость)": "Государственная",
    "Адрес недвижимости": "алл. Семашко, д.126, кв.20",
    "Площадь (кв.м)": 282,
    "Основание приобретения (недвижимость)": "Дарение",
    "Стоимость (недвижимость)": 1961366,
    "Залог (недвижимость)": "Нет",
    "Тип транспортного средства": "Мототранспортное средство",
    "Марка (транспорт)": "Королева и партнеры",
    "Год изготовления (транспорт)": 2002,
    "Идентификационный номер (VIN)": "hej-232244",
    "Вид собственности (транспорт)": "Муниципальная",
    "Место нахождения/хранения (транспорт)": "п. Стерлитамак, пр. Мирный, д. 39, 602867",
    "Стоимость (транспорт)": 3318269,
    "Залог (транспорт)": "Нет",
    "Наименование банка/кредитной организации": "РАО «Стрелков» Банк",
    "Адрес банка/кредитной организации": "с. Саратов, ул. Заозерная, д. 4/8, 428746",
    "Вид счета": "Депозитный счет",
    "Валюта счета": "RUB",
    "Дата открытия счета": "5/28/2015",
    "Остаток на счете (руб.)": 3917489,
    "Наименование организации": "Жуков и партнеры",
    "Организационно-правовая форма": "ООО",
    "Адрес организации": "д. Нефедова, пер. Крайний, д. 49 к. 2, 920235",
    "Уставный капитал (руб.)": 2460316,
    "Паевой фонд (руб.)": 12414445,
    "Доля участия (%)": "Jul-13",
    "Основание участия": "Покупка акций",
    "Вид ценной бумаги": "Облигация",
    "Лицо выпустившее ценную бумагу": "Дементьев Групп",
    "Номинальная величина обязательства (руб)": 4759,
    "Общее количество": 709,
    "Общая стоимость (руб)": 245813,
    "Наличные денежные средства": 174584,
    "Адрес хранения наличных": "бул. Малиновый, д.185",
    "Драгоценности": 241777,
    "Адрес хранения драгоценностей": "пер. Поперечный, д.152",
    "Предметы искусства": 109811,
    "Адрес хранения предметов искусства": "ш. О.Кошевого, д.101",
    "Имущество для профессиональных занятий": 63325,
    "Адрес хранения имущества": "ул. Разина, д.63",
    "Иное ценное имущество": 196020,
    "Адрес хранения иного имущества": "алл. Тракторная, д.16",
    "Ссылка на документ": "https://docs.google.com/document/d/1WFx_MwWY1uRLg7IHRhdN0wjb5eIV9g_pS_vNpfHKr5k/edit?usp=sharing",
    "ID": "d7848a17-c216-4350-a23d-3c95a72895d9"
}